swapdb/__init__.py
swapdb-0.0.31.dist-info/LICENSE
swapdb-0.0.31.dist-info/METADATA
swapdb-0.0.31.dist-info/WHEEL
swapdb-0.0.31.dist-info/top_level.txt
swapdb-0.0.31.dist-info/RECORD
