Metadata-Version: 2.1
Name: swapdb
Version: 0.0.31
Summary: Easy-to-use database, that stored in JSON file
Home-page: https://github.com/redleader167/swapdb
Author: R3D
Author-email: thatkenux@gmail.com
License: UNKNOWN
Project-URL: Bug Tracker, https://github.com/redleader167/swapdb/issues
Platform: UNKNOWN
Classifier: Programming Language :: Python :: 3
Classifier: License :: OSI Approved :: MIT License
Classifier: Operating System :: OS Independent
Requires-Python: >=3.6
License-File: LICENSE
